strands_cloudflare/__init__.py
strands_cloudflare/use_cloudflare.py
strands_cloudflare-0.2.0.dist-info/licenses/LICENSE
strands_cloudflare-0.2.0.dist-info/METADATA
strands_cloudflare-0.2.0.dist-info/WHEEL
strands_cloudflare-0.2.0.dist-info/top_level.txt
strands_cloudflare-0.2.0.dist-info/RECORD
