Metadata-Version: 2.4
Name: strands-cloudflare
Version: 0.2.0
Summary: Universal Cloudflare tool for Strands Agents - manage Zones, DNS, Workers, KV, R2, D1, Pages, AI, Tunnels and other services.
Author-email: Hashtag World <dev@hashtagworld.co>
License-Expression: Apache-2.0
Project-URL: Homepage, https://github.com/mertozbas/strands-cloudflare
Project-URL: Repository, https://github.com/mertozbas/strands-cloudflare
Project-URL: Issues, https://github.com/mertozbas/strands-cloudflare/issues
Project-URL: Documentation, https://github.com/mertozbas/strands-cloudflare#readme
Keywords: cloudflare,strands,strands-agents,ai-agent,workers,dns,cdn,serverless,edge-computing,zero-trust,tunnels,r2,d1,kv,pages
Classifier: Development Status :: 4 - Beta
Classifier: Intended Audience :: Developers
Classifier: Programming Language :: Python :: 3
Classifier: Programming Language :: Python :: 3.9
Classifier: Programming Language :: Python :: 3.10
Classifier: Programming Language :: Python :: 3.11
Classifier: Programming Language :: Python :: 3.12
Classifier: Programming Language :: Python :: 3.13
Classifier: Topic :: Internet :: WWW/HTTP
Classifier: Topic :: Software Development :: Libraries :: Python Modules
Classifier: Topic :: System :: Networking
Requires-Python: >=3.9
License-File: LICENSE
Requires-Dist: strands-agents
Requires-Dist: cloudflare>=3.0.0
Provides-Extra: dev
Requires-Dist: pytest>=7.0; extra == "dev"
Requires-Dist: pytest-asyncio>=0.21; extra == "dev"
Requires-Dist: black>=23.0; extra == "dev"
Requires-Dist: ruff>=0.1; extra == "dev"
Dynamic: license-file
